setup.py
docker_update/__init__.py
docker_update.egg-info/PKG-INFO
docker_update.egg-info/SOURCES.txt
docker_update.egg-info/dependency_links.txt
docker_update.egg-info/entry_points.txt
docker_update.egg-info/requires.txt
docker_update.egg-info/top_level.txt