Metadata-Version: 1.1
Name: docker-update
Version: 0.1.0
Summary: Generate commands you need to upgrade your docker containers
Home-page: https://github.com/iamfat/docker-update
Author: Jia Huang
Author-email: iamfat@gmail.com
License: MIT
Keywords: docker update parse upgrade
Platform: UNKNOWN
Classifier: Development Status :: 3 - Alpha
Classifier: Intended Audience :: Developers
Classifier: Topic :: Utilities
Classifier: License :: OSI Approved :: MIT License
